milvus/__init__.py
milvus/settings.py
milvus/client/Abstract.py
milvus/client/Client.py
milvus/client/Exceptions.py
milvus/client/Status.py
milvus/client/__init__.py
milvus/client/utils.py
milvus/thrift/MilvusService.py
milvus/thrift/__init__.py
milvus/thrift/constants.py
milvus/thrift/ttypes.py
milvus_test-0.1.1.dist-info/LICENSE
milvus_test-0.1.1.dist-info/METADATA
milvus_test-0.1.1.dist-info/WHEEL
milvus_test-0.1.1.dist-info/top_level.txt
milvus_test-0.1.1.dist-info/RECORD
