Metadata-Version: 2.1
Name: milvus-test
Version: 0.1.1
Summary: Python Sdk for Milvus; Test version
Home-page: https://github.com/milvus-io/pymilvus
License: Apache-2.0
Platform: UNKNOWN
Classifier: Programming Language :: Python :: 3.4
Classifier: Programming Language :: Python :: 3.5
Classifier: Programming Language :: Python :: 3.6
Classifier: Programming Language :: Python :: 3.7
Requires-Python: >=3.4
Requires-Dist: thrift
